audearch/__init__.py
audearch/analyzer.py
audearch/database.py
audearch/register.py
audearch/search.py
tests/__init__.py
tests/conftest.py
tests/test_analyzer.py
tests/test_database.py
tests/test_register.py
tests/test_search.py
audearch-0.3.3.dist-info/LICENCE
audearch-0.3.3.dist-info/METADATA
audearch-0.3.3.dist-info/WHEEL
audearch-0.3.3.dist-info/top_level.txt
audearch-0.3.3.dist-info/RECORD
