Metadata-Version: 2.1
Name: audearch
Version: 0.3.3
Summary: audearch is a simple music search system
Home-page: https://github.com/audearch/audearch
Author: Jumpei Funayama
Author-email: contact.zouri.music@gmail.com
License: UNKNOWN
Platform: UNKNOWN
Classifier: Development Status :: 4 - Beta
Classifier: License :: OSI Approved :: MIT License
Classifier: Programming Language :: Python :: 3.6
Classifier: Programming Language :: Python :: 3.7
Classifier: Programming Language :: Python :: 3.8
Requires-Dist: tqdm
Requires-Dist: librosa
Requires-Dist: numpy
Requires-Dist: scipy
Requires-Dist: pymongo
Requires-Dist: toml
